touchphat/__init__.py
touchphat-0.0.2.dist-info/LICENSE.txt
touchphat-0.0.2.dist-info/METADATA
touchphat-0.0.2.dist-info/WHEEL
touchphat-0.0.2.dist-info/top_level.txt
touchphat-0.0.2.dist-info/RECORD
